MANIFEST.in
README.rst
setup.cfg
setup.py
tox.ini
leon/__init__.py
leon/arg_conversions.py
leon/file_change_watcher.py
leon/py_2vs3_utils.py
leon/web_handler.py
leon.egg-info/PKG-INFO
leon.egg-info/SOURCES.txt
leon.egg-info/dependency_links.txt
leon.egg-info/requires.txt
leon.egg-info/top_level.txt
leon.egg-info/zip-safe
leon/tests/__init__.py
leon/tests/test_arg_conversions.py
leon/tests/test_file_change_watcher.py
leon/tests/test_web_handler.py