Metadata-Version: 1.0
Name: leon
Version: 0.4.4
Summary: Simple Web Framework for RPC/REST-oriented Web Applications
Home-page: http://leon.io
Author: Roman Roelofsen
Author-email: romanroe@gmail.com
License: UNKNOWN
Platform: UNKNOWN
